{
  "type": "minecraft:crafting_shaped",
  "pattern": [
    "0 2",
    "345",
    "678"
  ],
  "key": {
    "0": {
      "item": "minecraft:iron_ingot"
    },
    "2": {
      "item": "minecraft:iron_ingot"
    },
    "3": {
      "item": "minecraft:blue_wool"
    },
    "4": {
      "item": "minecraft:iron_chestplate"
    },
    "5": {
      "item": "minecraft:blue_wool"
    },
    "6": {
      "item": "minecraft:iron_ingot"
    },
    "7": {
      "item": "minecraft:iron_ingot"
    },
    "8": {
      "item": "minecraft:iron_ingot"
    }
  },
  "result": {
    "item": "jet_and_elias_armors:knight_f_blue_chestplate",
    "count": 1
  }
}