{
  "type": "create:sequenced_assembly",
  "ingredient": {
    "item": "minecraft:diamond_axe"
  },
  "transitionalItem": {
    "item": "minecraft:diamond_axe"
  },
  "sequence": [
    {
      "type": "create:deploying",
      "ingredients": [
        {
          "item": "minecraft:diamond_axe"
        },
        {
          "item": "createchromaticreturn:handle_cast"
        }
      ],
      "results": [
        {
          "item": "minecraft:diamond_axe"
        }
      ]
    },
    {
      "type": "create:filling",
      "ingredients": [
        {
          "item": "minecraft:diamond_axe"
        },
        {
          "fluid": "createbigcannons:molten_steel",
          "amount": 300
        }
      ],
      "results": [
        {
          "item": "minecraft:diamond_axe"
        }
      ]
    },
    {
      "type": "create:pressing",
      "ingredients": [
        {
          "item": "minecraft:diamond_axe"
        }
      ],
      "results": [
        {
          "item": "minecraft:diamond_axe"
        }
      ]
    },
    {
      "type": "create:pressing",
      "ingredients": [
        {
          "item": "minecraft:diamond_axe"
        }
      ],
      "results": [
        {
          "item": "minecraft:diamond_axe"
        }
      ]
    },
    {
      "type": "create:filling",
      "ingredients": [
        {
          "item": "minecraft:diamond_axe"
        },
        {
          "fluid": "minecraft:water",
          "nbt": {},
          "amount": 1000
        }
      ],
      "results": [
        {
          "item": "minecraft:diamond_axe"
        }
      ]
    }
  ],
  "results": [
    {
      "item": "simplyswords:diamond_greataxe"
    }
  ],
  "loops": 1
}